djangocms_transfer/__init__.py
djangocms_transfer/apps.py
djangocms_transfer/cms_plugins.py
djangocms_transfer/cms_toolbars.py
djangocms_transfer/compat.py
djangocms_transfer/datastructures.py
djangocms_transfer/exporter.py
djangocms_transfer/forms.py
djangocms_transfer/importer.py
djangocms_transfer/utils.py
djangocms_transfer/static/djangocms_transfer/css/transfer.css
djangocms_transfer/templates/djangocms_transfer/import_plugins.html
djangocms_transfer/templates/djangocms_transfer/placeholder_close_frame.html
djangocms_transfer-2.0.1.dist-info/licenses/LICENSE
djangocms_transfer-2.0.1.dist-info/METADATA
djangocms_transfer-2.0.1.dist-info/WHEEL
djangocms_transfer-2.0.1.dist-info/top_level.txt
djangocms_transfer-2.0.1.dist-info/RECORD
